{
  "Users": [
    {
      "Id": 1,
      "UserName": "Nural",
      "Password": null
    },
    {
      "Id": 2,
      "UserName": "nural7h",
      "Password": null
    },
    {
      "Id": 3,
      "UserName": "nuriG",
      "Password": null
    },
    {
      "Id": 4,
      "UserName": "nuralVia",
      "Password": null
    },
    {
      "Id": 5,
      "UserName": "fernandes21",
      "Password": "123321"
    },
    {
      "Id": 6,
      "UserName": "nur_hsn",
      "Password": "password"
    },
    {
      "Id": 7,
      "UserName": "nural_hasan",
      "Password": "password"
    },
    {
      "Id": 8,
      "UserName": "lala",
      "Password": "1234"
    },
    {
      "Id": 9,
      "UserName": "julija",
      "Password": "1234"
    }
  ],
  "Posts": [
    {
      "Id": 4,
      "Owner": {
        "Id": 5,
        "UserName": "fernandes21",
        "Password": "123321"
      },
      "Title": "hello im fernandes",
      "Content": "no contant"
    },
    {
      "Id": 5,
      "Owner": {
        "Id": 7,
        "UserName": "nural_hasan",
        "Password": "password"
      },
      "Title": "nural top g",
      "Content": "hello"
    },
    {
      "Id": 6,
      "Owner": {
        "Id": 8,
        "UserName": "lala",
        "Password": "1234"
      },
      "Title": "test",
      "Content": "does it work"
    }
  ]
}